{
  "echo": {},
  "request": {
    "response_format": "json",
    "requestType": "U",
    "msgID": "484a2a98-357f-4002-997c-3633e3378762",
    "data": {
      "searchStr": "reliance",
      "subFilter": "Source|NSE",
      "filterBy": "all",
      "pageNo": "1"
    },
    "appID": "169fd42ab825341a351381cf08606e3a",
    "formFactor": "M"
  },
  "response": {
    "svcName": "SearchStockNotes",
    "serverTime": "1513853196368",
    "infoID": "0",
    "data": {
      "pictures": [
        {
          "dispExpDate": "-",
          "mediaType": "-",
          "instrument": "-",
          "eventDate": "",
          "displayStrikePrice": "-",
          "mediaURL": "-",
          "sentiment": "Neutral",
          "dispInstType": "-",
          "headline": "Clarification sought from Reliance Communications Ltd",
          "change": "0.70",
          "newsID": "06584d13947df2b0d9f8c574c3be7ea3",
          "changePer": "4.05",
          "exc": "BSE",
          "lTP": "17.97",
          "newsURL": "",
          "source": "BSE",
          "symbol": "532712_BSE",
          "udpateTime": "20 Dec 2017, 16:11 PM",
          "thumbNailUrl": "-",
          "optionType": "-",
          "symName": "RCOM",
          "shareURL": "http://103.210.194.141/news/RCOM/532712_BSE/Clarification-sought-from-Reliance-Communications-Ltd?id=06584d13947df2b0d9f8c574c3be7ea3",
          "secContracts": [
            {
              "symbol": "22_NSE",
              "symName": "ACC"
            }
          ]
        }
      ],
      "contracts": [
        {
          "tradingSymbol": "RELIANCE-EQ",
          "dispName": "RELIANCE",
          "sortPriority": 1,
          "symbol": "2885_NSE",
          "sortTwo": 1,
          "changePer": "-0.57",
          "associatedSymbol": [
            {
              "exc": "BSE",
              "symName": "RELIANCE",
              "symbol": "500325_BSE"
            }
          ],
          "symName": "RELIANCE",
          "change": "-5.20",
          "dispLen": "8",
          "istradeableIndex": false,
          "lTP": "912.95",
          "exc": "NSE",
          "companyName": "RELIANCE INDUSTRIES LTD"
        }
      ],
      "videos": [
        {
          "dispExpDate": "-",
          "mediaType": "-",
          "instrument": "-",
          "eventDate": "",
          "displayStrikePrice": "-",
          "mediaURL": "-",
          "sentiment": "Neutral",
          "dispInstType": "-",
          "headline": "Clarification sought from Reliance Communications Ltd",
          "change": "0.70",
          "newsID": "06584d13947df2b0d9f8c574c3be7ea3",
          "changePer": "4.05",
          "exc": "BSE",
          "lTP": "17.97",
          "newsURL": "",
          "source": "BSE",
          "symbol": "532712_BSE",
          "udpateTime": "20 Dec 2017, 16:11 PM",
          "thumbNailUrl": "-",
          "optionType": "-",
          "symName": "RCOM",
          "shareUrl": "http://103.210.194.141/news/RCOM/532712_BSE/Clarification-sought-from-Reliance-Communications-Ltd?id=06584d13947df2b0d9f8c574c3be7ea3",
          "secContracts": [
            {
              "symbol": "22_NSE",
              "symName": "ACC"
            }
          ]
        }
      ],
      "notes": [
        {
          "dispExpDate": "-",
          "mediaType": "-",
          "instrument": "-",
          "eventDate": "",
          "displayStrikePrice": "-",
          "mediaURL": "-",
          "sentiment": "Neutral",
          "dispInstType": "-",
          "headline": "Intraday reports for Reliance Infrastructure Ltd.(RELINFRA, 500390) Stock & Share Prices - December 20, 2017",
          "change": "38.85",
          "newsID": "622f504a8fec43c925117f851f1cfef7",
          "changePer": "8.33",
          "exc": "NSE",
          "lTP": "505.05",
          "newsURL": "https://www.outlookindia.com/outlookmoney/stockmarket/reliance-infrastructure-ltd-relinfra-500390/2017-12-20",
          "source": "OutlookIndia",
          "symbol": "553_NSE",
          "udpateTime": "20 Dec 2017, 14:04 PM",
          "thumbNailUrl": "-",
          "optionType": "-",
          "symName": "RELINFRA",
          "shareUrl": "http://103.210.194.141/news/RELINFRA/553_NSE/Intraday-reports-for-Reliance-Infrastructure-Ltd.%28RELINFRA%2C-500390%29-Stock-%26-Share-Prices---December-20%2C-2017?id=622f504a8fec43c925117f851f1cfef7",
          "secContracts": [
            {
              "symbol": "22_NSE",
              "symName": "ACC"
            }
          ]
        }
      ],
      "documents": [
        {
          "dispExpDate": "-",
          "mediaType": "-",
          "instrument": "-",
          "eventDate": "",
          "displayStrikePrice": "-",
          "mediaURL": "-",
          "sentiment": "Neutral",
          "dispInstType": "-",
          "headline": "Intraday reports for Reliance Infrastructure Ltd.(RELINFRA, 500390) Stock & Share Prices - December 20, 2017",
          "change": "38.85",
          "newsID": "622f504a8fec43c925117f851f1cfef7",
          "changePer": "8.33",
          "exc": "NSE",
          "lTP": "505.05",
          "newsURL": "https://www.outlookindia.com/outlookmoney/stockmarket/reliance-infrastructure-ltd-relinfra-500390/2017-12-20",
          "source": "OutlookIndia",
          "symbol": "553_NSE",
          "udpateTime": "20 Dec 2017, 14:04 PM",
          "thumbNailUrl": "-",
          "optionType": "-",
          "symName": "RELINFRA",
          "shareUrl": "http://103.210.194.141/news/RELINFRA/553_NSE/Intraday-reports-for-Reliance-Infrastructure-Ltd.%28RELINFRA%2C-500390%29-Stock-%26-Share-Prices---December-20%2C-2017?id=622f504a8fec43c925117f851f1cfef7",
          "secContracts": [
            {
              "symbol": "22_NSE",
              "symName": "ACC"
            }
          ]
        }
      ],
      "source": [
        "NSE",
        "BSE"
      ]
    },
    "appID": "169fd42ab825341a351381cf08606e3a",
    "msgID": "3686bbb0-e50f-49ba-b999-038def8b706c",
    "svcGroup": "StockNotes"
  },
  "config": {
    "label": 4,
    "message": 251,
    "menu": 78,
    "app": 110
  }
}