{
	"echo": {},
		"request": {
			"appID": "f24c543af510aea86e1f4413687ab5b6",
			"data": {
				"symbol": "849179_BFO"
			}
		},
		"response": {
			"svcName": "FutureChain",
			"serverTime": "1492672708903",
			"infoID": "0",
			"data": {
				"relatedContracts": [
				{
					"tradingSymbol": "BAJT17APRFUT",
					"expiry": "27 APR 2017",
					"symbol": "849179_BFO",
					"changePer": "-",
					"dispInstType": "FUTSTK",
					"associatedSymbol": [
					{
						"exc": "NFO",
						"symbol": "46171_NFO"
					}
					],
						"symName": "BAJAJ-AUTO",
						"dispExpDate": "27APR2017",
						"change": "-",
						"lTP": "-",
						"exc": "BFO",
						"instrument": "FUTSTK"
				}
				],
					"details": [
					{
						"tradingSymbol": "BAJT17JUNFUT",
						"expiry": "29 JUN 2017",
						"symbol": "820848_BFO",
						"changePer": "-",
						"dispInstType": "FUTSTK",
						"associatedSymbol": [
						{
							"exc": "NFO",
							"symbol": "45782_NFO"
						}
						],
							"symName": "BAJAJ-AUTO",
							"dispExpDate": "29JUN2017",
							"change": "-",
							"lTP": "-",
							"exc": "BFO",
							"instrument": "FUTSTK"
					}
				]
			},
			"appID": "f24c543af510aea86e1f4413687ab5b6",
			"msgID": "f010bd91-f037-4c10-b2a8-5b91403adea0",
			"svcGroup": "Quotes"
		},
		"config": {
			"label": 4,
			"message": 117,
			"menu": 49,
			"app": 35
		}
}
